zymbitwalletsdk/Account.py
zymbitwalletsdk/EllipticCurve.py
zymbitwalletsdk/EthAccount.py
zymbitwalletsdk/EthConnect.py
zymbitwalletsdk/EthTransaction.py
zymbitwalletsdk/Keyring.py
zymbitwalletsdk/ZymbitEthKeyring.py
zymbitwalletsdk/ZymbitKeyringManager.py
zymbitwalletsdk/__init__.py
zymbitwalletsdk-1.0.0.dist-info/METADATA
zymbitwalletsdk-1.0.0.dist-info/WHEEL
zymbitwalletsdk-1.0.0.dist-info/licenses/LICENSE.md
zymbitwalletsdk-1.0.0.dist-info/RECORD
