Metadata-Version: 2.1
Name: zymbitwalletsdk
Version: 1.0.0
Summary: Zymbit Wallet Python SDK
Project-URL: Homepage, https://github.com/Zymbit-Wallet/Zymbit-Wallet-Python-SDK
Author-email: Shivaansh Kapoor <shiv@zymbit.com>
License-File: LICENSE.md
Classifier: License :: OSI Approved :: Apache Software License
Classifier: Operating System :: OS Independent
Classifier: Programming Language :: Python :: 3
Requires-Python: >=3.7
